{"cameraMode":{"drawMode":0,"name":"Shaded","section":"Shading Mode"},"sceneLighting":true,"audioPlay":false,"sceneViewState":{"showFog":true,"showMaterialUpdate":false,"showSkybox":true,"showFlares":true,"showImageEffects":true,"showParticleSystems":true},"in2DMode":false,"pivot":{"x":-5.7047600746154789,"y":6.424300670623779,"z":2.9461543560028078},"rotation":{"x":-0.11226540058851242,"y":0.008959517814218998,"z":-0.0010128621943295003,"w":-0.9936373829841614},"size":4.041658401489258,"orthographic":false}